baml_cc_py-0.209.0.10.dist-info/METADATA
baml_cc_py-0.209.0.10.dist-info/WHEEL
baml_cc_py-0.209.0.10.dist-info/entry_points.txt
baml_cc_py-0.209.0.10.dist-info/licenses/LICENSE
baml_py/py.typed
baml_py/safe_import.py
baml_py/stream.py
baml_py/logging.py
baml_py/baml_py.pyi
baml_py/internal_monkeypatch.py
baml_py/__init__.py
baml_py/__pycache__/ctx_manager.cpython-312.pyc
baml_py/__pycache__/ctx_manager.cpython-311.pyc
baml_py/__pycache__/safe_import.cpython-312.pyc
baml_py/__pycache__/safe_import.cpython-311.pyc
baml_py/__pycache__/type_builder.cpython-312.pyc
baml_py/__pycache__/__init__.cpython-312.pyc
baml_py/__pycache__/__init__.cpython-311.pyc
baml_py/__pycache__/type_builder.cpython-311.pyc
baml_py/__pycache__/stream.cpython-312.pyc
baml_py/__pycache__/logging.cpython-312.pyc
baml_py/__pycache__/logging.cpython-311.pyc
baml_py/__pycache__/stream.cpython-311.pyc
baml_py/errors.py
baml_py/ctx_manager.py
baml_py/type_builder.py
baml_py/baml_py.abi3.so
baml_cc_py-0.209.0.10.dist-info/RECORD
