Metadata-Version: 2.3
Name: baml-cc-py
Version: 0.209.0.10
Requires-Dist: pytest >=8.4.2
License-File: LICENSE
Summary: BAML python bindings (pyproject.toml)
Author: Boundary <contact@boundaryml.com>
Author-email: Boundary <contact@boundaryml.com>
License: Apache-2.0
